message_channel/__init__.py
message_channel/channel.py
message_channel/exceptions.py
message_channel/router.py
python_message_channel-0.2.3.dist-info/LICENSE
python_message_channel-0.2.3.dist-info/WHEEL
python_message_channel-0.2.3.dist-info/METADATA
python_message_channel-0.2.3.dist-info/RECORD
