Metadata-Version: 2.1
Name: python-message-channel
Version: 0.2.3
Summary: Generic asynchronous message channel with routing by predicators
Home-page: https://github.com/fixpoint/python-message-channel
License: MIT
Author: Alisue
Author-email: lambdalisue@hashnote.net
Requires-Python: >=3.9,<4.0
Classifier: License :: OSI Approved :: MIT License
Classifier: Programming Language :: Python :: 3
Classifier: Programming Language :: Python :: 3.9
Project-URL: Documentation, https://fixpoint.github.io/python-message-channel/
Project-URL: Repository, https://github.com/fixpoint/python-message-channel
